amaceing_toolkit/__init__.py
amaceing_toolkit/default_configs/__init__.py
amaceing_toolkit/default_configs/cp2k_configs.py
amaceing_toolkit/default_configs/cp2k_kind_data.py
amaceing_toolkit/default_configs/grace_configs.py
amaceing_toolkit/default_configs/hpc_setup_path.txt
amaceing_toolkit/default_configs/mace_configs.py
amaceing_toolkit/default_configs/mace_e0s.py
amaceing_toolkit/default_configs/mattersim_configs.py
amaceing_toolkit/default_configs/orb_configs.py
amaceing_toolkit/default_configs/runscript_loader.py
amaceing_toolkit/default_configs/sevennet_configs.py
amaceing_toolkit/default_configs/__pycache__/__init__.cpython-39.pyc
amaceing_toolkit/default_configs/__pycache__/cp2k_configs.cpython-39.pyc
amaceing_toolkit/default_configs/__pycache__/cp2k_kind_data.cpython-39.pyc
amaceing_toolkit/default_configs/__pycache__/grace_configs.cpython-39.pyc
amaceing_toolkit/default_configs/__pycache__/mace_configs.cpython-39.pyc
amaceing_toolkit/default_configs/__pycache__/mace_e0s.cpython-39.pyc
amaceing_toolkit/default_configs/__pycache__/mattersim_configs.cpython-39.pyc
amaceing_toolkit/default_configs/__pycache__/orb_configs.cpython-39.pyc
amaceing_toolkit/default_configs/__pycache__/runscript_loader.cpython-39.pyc
amaceing_toolkit/default_configs/__pycache__/runscript_templates.cpython-39.pyc
amaceing_toolkit/default_configs/__pycache__/sevennet_configs.cpython-39.pyc
amaceing_toolkit/default_configs/__pycache__/uma_configs.cpython-39.pyc
amaceing_toolkit/default_configs/runscript_templates/cp2k
amaceing_toolkit/default_configs/runscript_templates/cp2k_local
amaceing_toolkit/default_configs/runscript_templates/grace_ft_gpu
amaceing_toolkit/default_configs/runscript_templates/grace_lmp_cpu
amaceing_toolkit/default_configs/runscript_templates/grace_lmp_gpu
amaceing_toolkit/default_configs/runscript_templates/grace_py_cpu
amaceing_toolkit/default_configs/runscript_templates/grace_py_gpu
amaceing_toolkit-0.6.0.dist-info/METADATA
amaceing_toolkit-0.6.0.dist-info/WHEEL
amaceing_toolkit-0.6.0.dist-info/entry_points.txt
amaceing_toolkit-0.6.0.dist-info/top_level.txt
amaceing_toolkit-0.6.0.dist-info/RECORD
amaceing_toolkit-0.6.0.dist-info/licenses/LICENSE
