Metadata-Version: 2.4
Name: amaceing_toolkit
Version: 0.6.0
Summary: A Python package for the creation of input files for CP2K, MACE-torch, MatterSim, SevenNet, ORB, and Grace as well as the post-processing and evaluation of these simulations.
Author-email: Jonas Hänseroth <jonas.haenseroth@tu-ilmenau.de>
License: MIT License (Non-Commercial Use Only)
Project-URL: Homepage, https://github.com/jhaens/amaceing_toolkit
Project-URL: Bug Tracker, https://github.com/jhaens/amaceing_toolkit/issues
Classifier: Programming Language :: Python :: 3
Classifier: License :: OSI Approved :: MIT License
Classifier: Operating System :: OS Independent
Requires-Python: >=3.9
License-File: LICENSE
Requires-Dist: ase==3.24.0
Requires-Dist: cycler==0.12.1
Requires-Dist: mace_torch==0.3.14
Requires-Dist: numpy==1.26.4
Requires-Dist: scipy==1.13.0
Requires-Dist: pybind11==2.13.6
Dynamic: license-file
Dynamic: requires-dist
